ojt/__init__.py
ojt/cli.py
ojt_data_generator-0.1.1.dist-info/licenses/LICENSE
ojt_data_generator-0.1.1.dist-info/METADATA
ojt_data_generator-0.1.1.dist-info/WHEEL
ojt_data_generator-0.1.1.dist-info/entry_points.txt
ojt_data_generator-0.1.1.dist-info/top_level.txt
ojt_data_generator-0.1.1.dist-info/RECORD
