Metadata-Version: 2.4
Name: ojt-data-generator
Version: 0.1.1
Summary: A powerful Python package for generating realistic fake data with 6 pre-built templates - perfect for testing, development, and prototyping
Home-page: https://github.com/kushalkotiny/ojt
Author: Kushal Kotiny
Author-email: kushalkotiny@example.com
Project-URL: Bug Reports, https://github.com/kushalkotiny/ojt/issues
Project-URL: Source, https://github.com/kushalkotiny/ojt
Keywords: fake data generator testing development faker mock data csv pandas
Classifier: Development Status :: 4 - Beta
Classifier: Intended Audience :: Developers
Classifier: Topic :: Software Development :: Testing
Classifier: Topic :: Software Development :: Libraries :: Python Modules
Classifier: Programming Language :: Python :: 3
Classifier: Programming Language :: Python :: 3.7
Classifier: Programming Language :: Python :: 3.8
Classifier: Programming Language :: Python :: 3.9
Classifier: Programming Language :: Python :: 3.10
Classifier: Programming Language :: Python :: 3.11
Classifier: License :: OSI Approved :: MIT License
Classifier: Operating System :: OS Independent
Requires-Python: >=3.7
License-File: LICENSE
Requires-Dist: faker>=18.0.0
Requires-Dist: pandas>=1.3.0
Dynamic: author
Dynamic: author-email
Dynamic: classifier
Dynamic: description
Dynamic: description-content-type
Dynamic: home-page
Dynamic: keywords
Dynamic: license-file
Dynamic: project-url
Dynamic: requires-dist
Dynamic: requires-python
Dynamic: summary
